{
  "product": "StatusDock",
  "incidents": [
    {
      "id": "i_1",
      "severity": "major",
      "status": "investigating",
      "timeline": [
        {
          "at": "2026-02-28T10:00:00Z",
          "event": "incident_opened"
        }
      ]
    }
  ],
  "update_cadence_minutes": 30,
  "notes": "incident contract placeholder - final",
  "loop_002_stage1": {
    "at": "2026-02-28T11:38:52Z",
    "product": "StatusDock",
    "worker": "worker-backend"
  },
  "loop_002_stage2": {
    "finalized_at": "2026-02-28T11:38:52Z",
    "status": "ready"
  },
  "loop_stage1": {
    "loop": "003",
    "at": "2026-02-28T11:46:13Z",
    "product": "StatusDock",
    "worker": "worker-backend"
  },
  "loop_stage2": {
    "loop": "003",
    "finalized_at": "2026-02-28T11:46:13Z",
    "status": "ready"
  }
}
